{
  "name": "Type B - Top Decoration",
  "description": "Decoration at top & bottom, text in middle area",
  "safeArea": {
    "topPct": 0.12,
    "bottomPct": 0.25,
    "leftPct": 0.14,
    "rightPct": 0.14
  },
  "defaultFonts": {
    "arabicFamily": "Amiri",
    "englishFamily": "Montserrat"
  },
  "textBlocks": [
    {
      "id": "intro_text",
      "boxPct": { "x": 0.14, "y": 0.12, "w": 0.72, "h": 0.10 },
      "font": { "familyKey": "arabic", "baseSize": 36, "minSize": 24, "weight": 400 },
      "color": "#6B6B6B",
      "align": "center",
      "lineHeight": 1.8,
      "letterSpacing": 0,
      "maxLines": 2,
      "autoFit": true
    },
    {
      "id": "invite_line",
      "boxPct": { "x": 0.14, "y": 0.23, "w": 0.72, "h": 0.07 },
      "font": { "familyKey": "arabic", "baseSize": 30, "minSize": 22, "weight": 400 },
      "color": "#6B6B6B",
      "align": "center",
      "lineHeight": 1.7,
      "letterSpacing": 0,
      "maxLines": 1,
      "autoFit": true
    },
    {
      "id": "groom_name",
      "boxPct": { "x": 0.18, "y": 0.33, "w": 0.64, "h": 0.08 },
      "font": { "familyKey": "arabic", "baseSize": 54, "minSize": 34, "weight": 400 },
      "color": "#6B6B6B",
      "align": "center",
      "lineHeight": 1.0,
      "letterSpacing": 0,
      "maxLines": 1,
      "autoFit": true
    },
    {
      "id": "bride_name",
      "boxPct": { "x": 0.18, "y": 0.41, "w": 0.64, "h": 0.08 },
      "font": { "familyKey": "arabic", "baseSize": 54, "minSize": 34, "weight": 400 },
      "color": "#6B6B6B",
      "lineHeight": 1.0,
      "letterSpacing": 0,
      "maxLines": 1,
      "autoFit": true,
      "align": "center"
    },
    {
      "id": "date_en",
      "boxPct": { "x": 0.34, "y": 0.50, "w": 0.32, "h": 0.05 },
      "font": { "familyKey": "english", "baseSize": 20, "minSize": 14, "weight": 400 },
      "color": "#6B6B6B",
      "align": "center",
      "lineHeight": 1.2,
      "letterSpacing": 0,
      "maxLines": 1,
      "autoFit": true
    },
    {
      "id": "verse_or_dua",
      "boxPct": { "x": 0.14, "y": 0.56, "w": 0.72, "h": 0.10 },
      "font": { "familyKey": "arabic", "baseSize": 28, "minSize": 18, "weight": 400 },
      "color": "#6B6B6B",
      "align": "center",
      "lineHeight": 1.8,
      "letterSpacing": 0,
      "maxLines": 3,
      "autoFit": true
    },
    {
      "id": "location_name",
      "boxPct": { "x": 0.14, "y": 0.67, "w": 0.72, "h": 0.06 },
      "font": { "familyKey": "arabic", "baseSize": 24, "minSize": 16, "weight": 400 },
      "color": "#6B6B6B",
      "align": "center",
      "lineHeight": 1.6,
      "letterSpacing": 0,
      "maxLines": 2,
      "autoFit": true
    }
  ]
}
